hpccm/Stage.py
hpccm/__init__.py
hpccm/base_object.py
hpccm/cli.py
hpccm/common.py
hpccm/config.py
hpccm/recipe.py
hpccm/toolchain.py
hpccm/version.py
hpccm/building_blocks/__init__.py
hpccm/building_blocks/amgx.py
hpccm/building_blocks/apt_get.py
hpccm/building_blocks/arm_allinea_studio.py
hpccm/building_blocks/base.py
hpccm/building_blocks/boost.py
hpccm/building_blocks/catalyst.py
hpccm/building_blocks/cgns.py
hpccm/building_blocks/charm.py
hpccm/building_blocks/cmake.py
hpccm/building_blocks/conda.py
hpccm/building_blocks/doca_ofed.py
hpccm/building_blocks/fftw.py
hpccm/building_blocks/gdrcopy.py
hpccm/building_blocks/generic_autotools.py
hpccm/building_blocks/generic_build.py
hpccm/building_blocks/generic_cmake.py
hpccm/building_blocks/gnu.py
hpccm/building_blocks/hdf5.py
hpccm/building_blocks/hpcx.py
hpccm/building_blocks/intel_mpi.py
hpccm/building_blocks/intel_psxe.py
hpccm/building_blocks/intel_psxe_runtime.py
hpccm/building_blocks/julia.py
hpccm/building_blocks/knem.py
hpccm/building_blocks/kokkos.py
hpccm/building_blocks/libsim.py
hpccm/building_blocks/llvm.py
hpccm/building_blocks/magma.py
hpccm/building_blocks/mkl.py
hpccm/building_blocks/mlnx_ofed.py
hpccm/building_blocks/mpich.py
hpccm/building_blocks/multi_ofed.py
hpccm/building_blocks/mvapich2.py
hpccm/building_blocks/mvapich2_gdr.py
hpccm/building_blocks/nccl.py
hpccm/building_blocks/netcdf.py
hpccm/building_blocks/nsight_compute.py
hpccm/building_blocks/nsight_systems.py
hpccm/building_blocks/nvhpc.py
hpccm/building_blocks/nvshmem.py
hpccm/building_blocks/ofed.py
hpccm/building_blocks/openblas.py
hpccm/building_blocks/openmpi.py
hpccm/building_blocks/packages.py
hpccm/building_blocks/pgi.py
hpccm/building_blocks/pip.py
hpccm/building_blocks/pmix.py
hpccm/building_blocks/pnetcdf.py
hpccm/building_blocks/python.py
hpccm/building_blocks/rdma_core.py
hpccm/building_blocks/scif.py
hpccm/building_blocks/sensei.py
hpccm-26.1.0.dist-info/DESCRIPTION.rst
hpccm-26.1.0.dist-info/METADATA
hpccm-26.1.0.dist-info/RECORD
hpccm-26.1.0.dist-info/WHEEL
hpccm-26.1.0.dist-info/entry_points.txt
hpccm-26.1.0.dist-info/metadata.json
hpccm-26.1.0.dist-info/top_level.txt
