Metadata-Version: 2.0
Name: hpccm
Version: 26.1.0
Summary: HPC Container Maker
Home-page: https://github.com/NVIDIA/hpc-container-maker
Maintainer: Scott McMillan
Maintainer-email: smcmillan@nvidia.com
License: Apache License Version 2.0
Platform: UNKNOWN
Classifier: License :: OSI Approved :: Apache Software License
Classifier: Programming Language :: Python :: 2
Classifier: Programming Language :: Python :: 2.7
Classifier: Programming Language :: Python :: 3
Classifier: Programming Language :: Python :: 3.4
Classifier: Programming Language :: Python :: 3.5
Classifier: Programming Language :: Python :: 3.6
Requires-Dist: archspec
Requires-Dist: packaging
Requires-Dist: six
Requires-Dist: enum34; python_version < "3.4"
